frame/__init__.py
frame/config.yaml
frame/frame.py
frame/util.py
frame/font/NotoSansSC-Bold.otf
frame/font/NotoSansSC-Regular.otf
frame/font/OFL.txt
frame/logo/NIKON CORPORATION.png
frame/logo/README.md
exif_frame-1.0.5.dist-info/LICENSE
exif_frame-1.0.5.dist-info/METADATA
exif_frame-1.0.5.dist-info/WHEEL
exif_frame-1.0.5.dist-info/entry_points.txt
exif_frame-1.0.5.dist-info/top_level.txt
exif_frame-1.0.5.dist-info/RECORD
