Metadata-Version: 2.1
Name: exif-frame
Version: 1.0.5
Home-page: https://github.com/cyan-io/exif-frame
Download-URL: https://github.com/cyan-io/exif-frame/releases
Author: Cyan@https://github.com/cyan-io
Author-email: cyan-io@outlook.com
License: MPL 2.0
Platform: any
Requires-Python: >=3.6
License-File: LICENSE
Requires-Dist: PyYAML
Requires-Dist: pillow
